{
  "distribution": {
    "auto": {
      "p25": 4.1,
      "p75": 13.2
    },
    "teleop": {
      "p25": 10.2,
      "p75": 53.5
    },
    "endgame": {
      "p25": 4.8,
      "p75": 16.1
    },
    "total": {
      "p25": 22.8,
      "p75": 76.3
    },
    "fouls": {
      "p25": -2.2,
      "p75": 3.3
    },
    "dpr": {
      "p25": 2.2,
      "p75": 94.6
    },
    "drive": {
      "p25": 2.0,
      "p75": 3.3
    },
    "defense": {
      "p25": 2.0,
      "p75": 3.0
    }
  },
  "teams": [
    {
      "team": 6045,
      "score": 178.5,
      "auto": 18.4,
      "teleop": 122.1,
      "endgame": 38.0,
      "drive_rank": 3.5,
      "defense_rank": 3.0,
      "breakdown": 0,
      "comments": " | Huge hopper takes a bit to fill up | "
    },
    {
      "team": 4728,
      "score": 170.4,
      "auto": 21.0,
      "teleop": 115.9,
      "endgame": 33.6,
      "drive_rank": 3.6,
      "defense_rank": 1.0,
      "breakdown": 1,
      "comments": " | Got stuck in auto huge hopper | Huge hopper | They have a very good intake and hopper and they are very fast | Large hopper | "
    },
    {
      "team": 876,
      "score": 159.2,
      "auto": 27.0,
      "teleop": 103.2,
      "endgame": 29.0,
      "drive_rank": 4.6,
      "defense_rank": 2.0,
      "breakdown": 0,
      "comments": "Great driver | Great driver | Great driver |  |  | Fast cycle | Fast cycle | They shoot the fuel then it it stops when there is still fuel in it then they shoot it again but they are fast with pick up"
    },
    {
      "team": 8255,
      "score": 138.1,
      "auto": 17.3,
      "teleop": 83.9,
      "endgame": 36.9,
      "drive_rank": 2.7,
      "defense_rank": "",
      "breakdown": 0,
      "comments": "Got stuck on fuel |  | "
    },
    {
      "team": 3276,
      "score": 137.5,
      "auto": 27.6,
      "teleop": 97.0,
      "endgame": 12.9,
      "drive_rank": 4.0,
      "defense_rank": "",
      "breakdown": 0,
      "comments": "Great passing and scoring "
    },
    {
      "team": 2883,
      "score": 129.4,
      "auto": 19.7,
      "teleop": 88.0,
      "endgame": 21.7,
      "drive_rank": 4.7,
      "defense_rank": "",
      "breakdown": 0,
      "comments": "Shooting while Intaking in outpost cornerHalf of field passing  | Smaller hopper but fast scoring and great passing | Passing"
    },
    {
      "team": 7028,
      "score": 128.0,
      "auto": 18.8,
      "teleop": 83.7,
      "endgame": 25.5,
      "drive_rank": 3.7,
      "defense_rank": 5.0,
      "breakdown": 0,
      "comments": "Heavy scoring | Good pick | Struggled under defense "
    },
    {
      "team": 2503,
      "score": 122.6,
      "auto": 16.4,
      "teleop": 77.9,
      "endgame": 28.3,
      "drive_rank": 3.8,
      "defense_rank": 3.8,
      "breakdown": 0,
      "comments": "Got Beached on fuel  | Got Beached on fuel  | Got Beached on fuel  | Got Beached on fuel  | Got Beached on fuel  | Got Beached on fuel  | Not many cycles but very large hopper | Got Beached on fuel  | Have a large hopper | Large hopper | Got Beached on fuel "
    },
    {
      "team": 5913,
      "score": 119.9,
      "auto": 21.1,
      "teleop": 81.2,
      "endgame": 17.5,
      "drive_rank": 2.8,
      "defense_rank": "",
      "breakdown": 1,
      "comments": "Fast shooter | Fast shooter | WAYYYYY over shot  | They got fuel quickly bIt the shooting goes to the ceiling and it doesn\u2019t make it in the tower | They got fuel quickly bIt the shooting goes to the ceiling and it doesn\u2019t make it in the tower | They got fuel quickly bIt the shooting goes to the ceiling and it doesn\u2019t make it in the tower | They got fuel quickly bIt the shooting goes to the ceiling and it doesn\u2019t make it in the tower | They got fuel quickly bIt the shooting goes to the ceiling and it doesn\u2019t make it in the tower | "
    },
    {
      "team": 6175,
      "score": 111.1,
      "auto": 14.7,
      "teleop": 75.0,
      "endgame": 21.5,
      "drive_rank": 3.6,
      "defense_rank": 3.0,
      "breakdown": 0,
      "comments": " |  |  |  | not much passing | Well rounded team | Well rounded team | Well rounded team"
    },
    {
      "team": 4607,
      "score": 102.7,
      "auto": 22.1,
      "teleop": 57.9,
      "endgame": 22.7,
      "drive_rank": 3.9,
      "defense_rank": 3.3,
      "breakdown": 1,
      "comments": " |  |  |  |  |  |  |  |  |  |  |  |  | Pretty neat team |  | They were quick and quick intake and in auto they went fuel surfing  | C: perfect robot | Fast cycle  | Really fast and quick at shooting and picking up they did had a fuel surf once "
    },
    {
      "team": 2509,
      "score": 96.1,
      "auto": 14.7,
      "teleop": 60.7,
      "endgame": 20.7,
      "drive_rank": 3.0,
      "defense_rank": "",
      "breakdown": 2,
      "comments": " | Auto failed but big hopper and scored lots | Tipped over after auto over the bump"
    },
    {
      "team": 5348,
      "score": 79.4,
      "auto": 11.2,
      "teleop": 52.6,
      "endgame": 15.6,
      "drive_rank": 3.2,
      "defense_rank": 3.0,
      "breakdown": 1,
      "comments": "Beached in neutral zone during autoL1 climbHit trench | Beached in neutral zone in auto |  | Broke down in red zone during first red shift  | Climbed "
    },
    {
      "team": 5837,
      "score": 73.3,
      "auto": 3.3,
      "teleop": 54.5,
      "endgame": 15.5,
      "drive_rank": 3.7,
      "defense_rank": 2.0,
      "breakdown": 1,
      "comments": "Fabric on top jammed into indexer | Kinda stayed in the neutral zone | Passed and shot full hoppers"
    },
    {
      "team": 6709,
      "score": 69.1,
      "auto": 7.0,
      "teleop": 43.5,
      "endgame": 18.6,
      "drive_rank": 3.8,
      "defense_rank": 2.0,
      "breakdown": 0,
      "comments": "Got beached in auto and teleop. | Turret bot | Turret bot |  | Got stuck on fuel"
    },
    {
      "team": 7578,
      "score": 64.3,
      "auto": 16.6,
      "teleop": 40.2,
      "endgame": 7.4,
      "drive_rank": 2.3,
      "defense_rank": "",
      "breakdown": 0,
      "comments": " | Missed shots | Intake broke off mid match"
    },
    {
      "team": 3018,
      "score": 59.3,
      "auto": 6.7,
      "teleop": 38.6,
      "endgame": 14.0,
      "drive_rank": 2.6,
      "defense_rank": "",
      "breakdown": 0,
      "comments": "Over shot majority of balls  |  Not the fastest but got a good hopper and decent accuracy  |  |  | Over shot too much | Over shot too much | They helped a lot with getting fuel but when they shoot it\u2019s a bit low and their medium with speed  | Over shot too much"
    },
    {
      "team": 4360,
      "score": 58.9,
      "auto": 7.3,
      "teleop": 34.8,
      "endgame": 16.7,
      "drive_rank": 2.5,
      "defense_rank": 2.0,
      "breakdown": 1,
      "comments": " | Indexer not working well"
    },
    {
      "team": 8821,
      "score": 50.5,
      "auto": 11.7,
      "teleop": 33.7,
      "endgame": 5.0,
      "drive_rank": 1.7,
      "defense_rank": 1.5,
      "breakdown": 0,
      "comments": "Slow scoring inaccurate  | Vary small hopper and kept running into things | "
    },
    {
      "team": 4226,
      "score": 48.4,
      "auto": 11.5,
      "teleop": 28.9,
      "endgame": 7.9,
      "drive_rank": 2.0,
      "defense_rank": 3.0,
      "breakdown": 1,
      "comments": " |  | Slow "
    },
    {
      "team": 2987,
      "score": 45.8,
      "auto": 11.5,
      "teleop": 25.9,
      "endgame": 8.4,
      "drive_rank": 2.0,
      "defense_rank": "",
      "breakdown": 0,
      "comments": "Over shot a lot | "
    },
    {
      "team": 2977,
      "score": 44.6,
      "auto": 4.7,
      "teleop": 28.0,
      "endgame": 11.9,
      "drive_rank": 2.5,
      "defense_rank": 3.0,
      "breakdown": 0,
      "comments": "Passing |  | Hopper didnt hold much | Mostly missed cycle shots"
    },
    {
      "team": 2470,
      "score": 42.9,
      "auto": 8.6,
      "teleop": 25.1,
      "endgame": 9.2,
      "drive_rank": 2.5,
      "defense_rank": 3.0,
      "breakdown": 0,
      "comments": " | Got stuck of fuel often. |  | "
    },
    {
      "team": 4687,
      "score": 41.5,
      "auto": 5.8,
      "teleop": 27.8,
      "endgame": 7.9,
      "drive_rank": 2.3,
      "defense_rank": "",
      "breakdown": 3,
      "comments": "No autoStopped in front of hub for last 1.5 minutes |  |  | Beached in auto."
    },
    {
      "team": 3026,
      "score": 40.2,
      "auto": 3.2,
      "teleop": 22.6,
      "endgame": 14.4,
      "drive_rank": 2.0,
      "defense_rank": 3.0,
      "breakdown": 1,
      "comments": " | They don\u2019t move on auto they just shoot a few times  in teleop they go slow and slow intake  | Broke down right after auto"
    },
    {
      "team": 2512,
      "score": 36.8,
      "auto": 2.3,
      "teleop": 26.2,
      "endgame": 8.3,
      "drive_rank": 1.0,
      "defense_rank": 2.0,
      "breakdown": 1,
      "comments": " | Stopped working | "
    },
    {
      "team": 8516,
      "score": 36.4,
      "auto": 8.4,
      "teleop": 16.9,
      "endgame": 11.1,
      "drive_rank": 2.6,
      "defense_rank": 2.3,
      "breakdown": 0,
      "comments": "Climbed L1 in endgame | Climbed L1 in endgame | Climbed L1 in endgame | Climbed L1 in endgame | Passed balls |  | Climbed in auto and endgame  | Climbed in auto and endgame  | They can hang and they went fuel surfing a few times and the a medium with shooting and collecting "
    },
    {
      "team": 6628,
      "score": 35.6,
      "auto": 3.9,
      "teleop": 23.1,
      "endgame": 8.6,
      "drive_rank": 1.7,
      "defense_rank": "",
      "breakdown": 1,
      "comments": " | Intake broke then full robot broke. |  | Got stuck on fuel"
    },
    {
      "team": 3610,
      "score": 34.1,
      "auto": 4.5,
      "teleop": 19.1,
      "endgame": 10.5,
      "drive_rank": 3.4,
      "defense_rank": 3.3,
      "breakdown": 0,
      "comments": " |  |  |  |  |  |  | Pushed to human player often | Slow shooter"
    },
    {
      "team": 10173,
      "score": 33.2,
      "auto": 4.3,
      "teleop": 18.7,
      "endgame": 10.3,
      "drive_rank": 2.0,
      "defense_rank": 2.0,
      "breakdown": 1,
      "comments": "Slow shooter  |  | Rookie team | "
    },
    {
      "team": 7541,
      "score": 32.4,
      "auto": 11.0,
      "teleop": 15.1,
      "endgame": 6.3,
      "drive_rank": 3.3,
      "defense_rank": 1.0,
      "breakdown": 0,
      "comments": " | Large hopper | "
    },
    {
      "team": 4632,
      "score": 31.1,
      "auto": 4.2,
      "teleop": 22.8,
      "endgame": 4.1,
      "drive_rank": "",
      "defense_rank": "",
      "breakdown": 0,
      "comments": ""
    },
    {
      "team": 4238,
      "score": 30.5,
      "auto": 4.3,
      "teleop": 17.1,
      "endgame": 9.2,
      "drive_rank": 2.5,
      "defense_rank": "",
      "breakdown": 2,
      "comments": "Appeared to not be functional  | Slow at cycling | Slow at cycling | Missed most shots and got beached for part of first shift"
    },
    {
      "team": 7048,
      "score": 29.7,
      "auto": 11.8,
      "teleop": 12.2,
      "endgame": 5.7,
      "drive_rank": 2.2,
      "defense_rank": 1.5,
      "breakdown": 0,
      "comments": "Got stuck on fuel | Pushed fuel to human player often | Shot to high  | They were not really accurate when shooting it took them a while to get fuel to turret "
    },
    {
      "team": 7677,
      "score": 29.1,
      "auto": 8.3,
      "teleop": 16.1,
      "endgame": 4.7,
      "drive_rank": 2.7,
      "defense_rank": "",
      "breakdown": 1,
      "comments": "Got stuck on fuel and had to get fished out by another robot. |  | "
    },
    {
      "team": 1816,
      "score": 28.7,
      "auto": 7.1,
      "teleop": 15.1,
      "endgame": 6.5,
      "drive_rank": 3.0,
      "defense_rank": 3.3,
      "breakdown": 5,
      "comments": "Good defense and scoring | Good defense and scoring | Good defense and scoring | Good defense and scoring | Good defense and scoring | Good defense and scoring | Good defense and scoring |  | Great defense  | Great defense  | Great defense  | Great defense  | They were doing well at the start then at the end they were doing good defense then there turret fell off | "
    },
    {
      "team": 4480,
      "score": 25.4,
      "auto": 8.7,
      "teleop": 9.8,
      "endgame": 6.9,
      "drive_rank": 2.2,
      "defense_rank": 3.0,
      "breakdown": 0,
      "comments": "Got stuck on fuel twice |  |  | "
    },
    {
      "team": 7038,
      "score": 23.0,
      "auto": 5.4,
      "teleop": 10.0,
      "endgame": 7.5,
      "drive_rank": 1.0,
      "defense_rank": 1.0,
      "breakdown": 2,
      "comments": "Intake broke | Very slow shooting  | Intake and shooter are slow | Didn\u2019t even shoot "
    },
    {
      "team": 4182,
      "score": 22.6,
      "auto": 3.6,
      "teleop": 10.2,
      "endgame": 8.8,
      "drive_rank": 1.7,
      "defense_rank": "",
      "breakdown": 1,
      "comments": "No auto | Was not shooting at the end of the of the match slow shooter  | Can climb"
    },
    {
      "team": 5232,
      "score": 18.9,
      "auto": 3.7,
      "teleop": 10.2,
      "endgame": 4.9,
      "drive_rank": 1.9,
      "defense_rank": 2.0,
      "breakdown": 5,
      "comments": "No autoPinning penaltyRobot disabled | No autoPinning penaltyRobot disabled | Seemed to be having trouble moving  |  | Looks like something broke slow shooting  | They take a long time to get fuel and shoot it and they barely were shooting it looked like there turret was stuck  | Browning out whole match"
    },
    {
      "team": 4511,
      "score": 17.6,
      "auto": 10.7,
      "teleop": 5.2,
      "endgame": 1.7,
      "drive_rank": 2.5,
      "defense_rank": 3.0,
      "breakdown": 0,
      "comments": "Inconsistent intake. | Pushed to human players often"
    },
    {
      "team": 3740,
      "score": 16.3,
      "auto": 0.8,
      "teleop": 11.1,
      "endgame": 4.4,
      "drive_rank": 2.0,
      "defense_rank": 3.0,
      "breakdown": 0,
      "comments": " | Slab!!! | "
    },
    {
      "team": 8887,
      "score": 14.8,
      "auto": 1.5,
      "teleop": 8.6,
      "endgame": 4.8,
      "drive_rank": 2.0,
      "defense_rank": "",
      "breakdown": 0,
      "comments": " |  | Shooting into itself"
    },
    {
      "team": 6244,
      "score": 12.8,
      "auto": 3.1,
      "teleop": 7.5,
      "endgame": 2.1,
      "drive_rank": 1.8,
      "defense_rank": 2.2,
      "breakdown": 0,
      "comments": " |  | Shooter was less than optimal | Intake was slow"
    },
    {
      "team": 3023,
      "score": 11.0,
      "auto": 4.0,
      "teleop": 5.0,
      "endgame": 2.1,
      "drive_rank": 1.7,
      "defense_rank": 1.5,
      "breakdown": 1,
      "comments": "Defense bad a score in | Got stuck on fuel often. | Didn\u2019t move | They cannot drive and they can\u2019t shoot well"
    },
    {
      "team": 5541,
      "score": 9.9,
      "auto": 4.9,
      "teleop": 4.8,
      "endgame": 0.2,
      "drive_rank": 1.8,
      "defense_rank": 2.0,
      "breakdown": 2,
      "comments": "Struggled driving slow shooting | Intake didn\u2019t work the whole match. Had problems surfing and getting beached | Pretty good defense  | They tried shooting but couldn\u2019t and they went to defense and it was okay then at the end they got stuck on the bump"
    },
    {
      "team": 3848,
      "score": 9.5,
      "auto": 5.7,
      "teleop": 2.8,
      "endgame": 1.0,
      "drive_rank": 2.0,
      "defense_rank": 3.0,
      "breakdown": 0,
      "comments": " | Not present"
    },
    {
      "team": 2538,
      "score": 8.9,
      "auto": 1.9,
      "teleop": 5.9,
      "endgame": 1.1,
      "drive_rank": 1.5,
      "defense_rank": 2.0,
      "breakdown": 0,
      "comments": "Slow scoreing small hopper | "
    },
    {
      "team": 8372,
      "score": 4.7,
      "auto": 3.8,
      "teleop": 0.9,
      "endgame": 0.0,
      "drive_rank": 1.0,
      "defense_rank": 2.0,
      "breakdown": 1,
      "comments": "No fuel shot in teleop. | Beached on fuel | "
    },
    {
      "team": 8188,
      "score": 3.4,
      "auto": 4.2,
      "teleop": -0.8,
      "endgame": 0.0,
      "drive_rank": 2.0,
      "defense_rank": "",
      "breakdown": 3,
      "comments": "Scored 4 fuelSat in front of the hub for the last minute | Scored 4 fuelSat in front of the hub for the last minute | Didn\u2019t move at all"
    },
    {
      "team": 2511,
      "score": 2.2,
      "auto": 2.3,
      "teleop": -0.6,
      "endgame": 0.6,
      "drive_rank": 2.0,
      "defense_rank": "",
      "breakdown": 1,
      "comments": "Shot one fuel and missed |  | Big hopper folded under defense "
    }
  ],
  "event_key": "2026mnmi2",
  "last_updated": "2026-04-10T20:00:24Z",
  "blend": {
    "played_quals": 36,
    "total_quals": 77,
    "epa_pct": 25,
    "copr_pct": 35,
    "prior_copr_pct": 40
  }
}